nonebot_plugin_gscode/__init__.py
nonebot_plugin_gscode/data_source.py
nonebot_plugin_gscode-0.2.2.dist-info/LICENSE
nonebot_plugin_gscode-0.2.2.dist-info/METADATA
nonebot_plugin_gscode-0.2.2.dist-info/WHEEL
nonebot_plugin_gscode-0.2.2.dist-info/RECORD
